paij/__init__.py
paij/functions.py
paij/main.py
paij-1.1.1.dist-info/LICENSE
paij-1.1.1.dist-info/METADATA
paij-1.1.1.dist-info/WHEEL
paij-1.1.1.dist-info/top_level.txt
paij-1.1.1.dist-info/RECORD
