Metadata-Version: 2.1
Name: paij
Version: 1.1.1
Summary: A Python library for generating Java methods from unit tests using OpenAI's GPT model.
Author-email: Mehmet Şahin <mehmetsahinn2002@gmail.com>
Project-URL: Homepage, https://github.com/mehmetsahinnn/PythonExampleJavaTestCreator
Project-URL: Issues, https://github.com/mehmetsahinnn/PythonExampleJavaTestCreator/issues
Classifier: Programming Language :: Python :: 3
Classifier: License :: OSI Approved :: MIT License
Classifier: Operating System :: OS Independent
Requires-Python: >=3.9
License-File: LICENSE
